saucenaopy/__init__.py
saucenaopy/limiter.py
saucenaopy/saucenao.py
saucenaopy/saucenaopy.py
saucenaopy-0.1.12.data/scripts/saucenaopy
saucenaopy-0.1.12.dist-info/DESCRIPTION.rst
saucenaopy-0.1.12.dist-info/METADATA
saucenaopy-0.1.12.dist-info/RECORD
saucenaopy-0.1.12.dist-info/WHEEL
saucenaopy-0.1.12.dist-info/metadata.json
saucenaopy-0.1.12.dist-info/top_level.txt
