Metadata-Version: 2.0
Name: saucenaopy
Version: 0.1.12
Summary: Python SauceNAO API wrapper
Home-page: https://github.com/ranthai/saucenaopy
Author: ranthai
Author-email: UNKNOWN
License: UNKNOWN
Platform: UNKNOWN
Requires-Dist: requests
